gdaicommons/__init__.py
gdaicommons/constants.py
gdaicommons/utils.py
gdaicommons/nlp/__init__.py
gdaicommons/nlp/fill_mask.py
gdaicommons/nlp/text2text_generation.py
gdaicommons/nlp/text_classification.py
gdaicommons/nlp/text_generation.py
gdaicommons/nlp/text_labelling.py
gdaicommons/nlp/text_summarization.py
gdaicommons/nlp/transformations.py
gdaicommons-0.0.9.dist-info/LICENSE
gdaicommons-0.0.9.dist-info/METADATA
gdaicommons-0.0.9.dist-info/WHEEL
gdaicommons-0.0.9.dist-info/top_level.txt
gdaicommons-0.0.9.dist-info/RECORD
